spacy_pat_match_dsl/__init__.py
spacy_pat_match_dsl/dsl.py
spacy_pat_match_dsl-1.0.0.dist-info/LICENSE
spacy_pat_match_dsl-1.0.0.dist-info/METADATA
spacy_pat_match_dsl-1.0.0.dist-info/WHEEL
spacy_pat_match_dsl-1.0.0.dist-info/top_level.txt
spacy_pat_match_dsl-1.0.0.dist-info/RECORD
