Metadata-Version: 2.1
Name: spacy-pat-match-dsl
Version: 1.0.0
Summary: DSL inside Python for spaCy rule-based pattern matching
Author-email: Ruslan Popov <ruslanpopov1512@gmail.com>
License: MIT License
Project-URL: Homepage, https://github.com/InAnYan/spacy_pat_match_dsl
Keywords: dsl
Classifier: License :: OSI Approved :: MIT License
Classifier: Programming Language :: Python
Classifier: Programming Language :: Python :: 3
Requires-Python: >=3.9
License-File: LICENSE
